pepito/__init__.py
pepito/checkin_service.py
pepito/checksum.py
pepito/checksum_service.py
pepito/delivery.py
pepito/diff_lines.py
pepito/diff_processor.py
pepito/diff_service.py
pepito/errors.py
pepito/git_commands.py
pepito/gms_file_headers_modifier.py
pepito/gms_file_headers_verifier.py
pepito/gms_files.py
pepito/models.py
pepito/reference_file.py
pepito/rtf_writer.py
pepito-0.1.1.dist-info/METADATA
pepito-0.1.1.dist-info/WHEEL
pepito-0.1.1.dist-info/entry_points.txt
pepito-0.1.1.dist-info/top_level.txt
pepito-0.1.1.dist-info/RECORD
