Metadata-Version: 2.4
Name: pepito
Version: 0.1.1
Summary: Migration of Perl scripts using Clearcase to Python scripts using Git
Author-email: "S. Jouffroy" <sjouffroy@sii.fr>
Requires-Python: >=3.10
Requires-Dist: typer>=0.15.2
Requires-Dist: rich>=13.8.1
Requires-Dist: pydantic>=2.10.6
